{"order-items": [{"item_price": "299.00", "modelid": "259405162-69480570", "id": "order-259405162-85380463-69480570", "amount": 1, "snapshotid": 111946741, "order_price": "299.00", "status": 1, "comm_fee_rate": "3.0", "is_wholesale": false}], "item-models": [{"modelid": 69480570, "promotionid": 1001363580, "currency": "TWD", "sku": "PWS-EAMS1818", "price_before_discount": "549.00", "stock": 46, "promo_stock": 0, "flash_sale_status": "empty", "price": "299.00", "itemid": 85380463, "name": "ä¸æ®ºâ1.8m", "flash_sale": null, "promotion_refresh_time": 1508515140, "rebate_price": "0.00", "status": 1, "id": "259405162-69480570"}], "products": [{"brand": "ç¾¤å Powersync ", "id": 111946741, "shopid": 10966219, "estimated_days": 3, "price_before_discount": "549.00", "sold": 40, "stock": 146, "images": ["9ad3a663db3a155db89d0e045cade4ea", "9c697d7f470a7079d7f66f2069279d80", "5ca710559e30c184f391c06673c3d3ee", "f526d368d0d37e4fb47f2ae30a8227b8", "424aade37df97024e4367ce85c0bff8a", "c77fe8c3b879be5131fd7790d32860bd", "7bff6eb6d9cfc6825eb84cf0b31a33b1", "d3393fac3279ab72f225b07e4b4c52de"], "currency": "TWD", "condition": 1, "price": "299.00", "itemid": 85380463, "name": "è¶æ®  ç¾¤å Powersync 18 2P+3P ²é·æç£µå»¶·ç PWS-EAMS1845", "is_pre_order": false, "cmt_count": 24, "ctime": 1478231552, "parent_sku": "PWS-EAMS1845", "status": 1, "liked_count": 34, "catid": 69, "description": ">>>>18 ²é·æçªæ³ å¼·åç£ »æå»¶é·çå¯¦éå®¤æå®¨æ¬¾<<<<<\n>>>>å¯¦éå®¤çç´å°¿çè³ªïæ¸¬è©¦é«850åº<<<<\n\n¢å¹è²\n\n å°¿ç²ç«é²çåº,é«850åº¦\n ç·¡ç¨VCTF 2.0mmÂ² ç²»ç\n é«ç¡¬åº¦ABS²çå¡å¤æ®¼\n çªæ³¢äè­·æ¸æ¶ç°å¸¸»åï¼ç©©å»æ\n ²é·æçªæ³¢äè­·LED\n ¢å¬éè¨­æºå¨èºçµ²å­ï¼äº¦å¯æ¹çµå¸éï¼©ç¨è²¼å¿è¨­è\n «æè²è¼ä¿è­·å½ïè²è¼ä½¿ç¨æªå·é»\n\n ï¼²é·æ3å­+2å­ 8å»¶é·ç(ç£µåºå)\n é¡å®å®¹éï¼15å®/125V/å¤§ä½¿¨å1650W\n åº§ï3å­-4¥å°æåº/2å­-4åº/1\n \n çªæ³¢å¸æ¶è½éï¼86¦è³\n ¬éé«¯æ¿å»æ¼ï3500å®¹\n ¬éé«¯æ¶é»å¼ï395ä¼¹\n å°ºå¯¸ï¼270(L)x50(W)x36(H)mm\n èªè­ï¼TP-3088C\n èªè­ç·¨ç¢¼ï¼R31022\n ¥å°çé¡²ïç¶/é»\n   å­ï¼2å­\n  è³ªï²ç«èABS\n è£½é¥æï¼å¦è£ä¸æ¨ç¤ / ä¿å­ï¼äºå¹´\n ä¿ºæï¼äººçºåç´ä¿ºäå¹´\n ä»ï¼ç¾¤å¡ä»½¬å / ¢å°ïä¸­å\n ¬ç¢åå·²æä¿ä¸¬ç¢åè²¬ä»»ªï¿äç¯°ãæ¾é¦¬ï\n ¬ç¢åï¼¢ï¼³ï¼­ï¼©å®¨æª¢é©¼\n\n#²é·æ #å® # #ç¾¤å #Powersync #å°  #äº #å»¶é·ç #è¨­è # #ç£"}], "users": [{"delivery_address_id": 55823, "shopid": 1292535, "holiday_mode_mtime": 0, "username": "moonoipoppi", "portrait": "436508684ebe8c92a1fc9758d8a4828c", "delivery_succ_count": 110, "products": -1, "phone_public": false, "phone": "886920330625", "holiday_mode": false, "delivery_order_count": 111, "ctime": 1445608450, "feed_private": false, "status": 1, "wholesale_setting": 1, "email": "claire.poppi@gmail.com", "gender": 0, "language": "zh-Hant", "pn_option": 4294967039, "id": 1293514, "fbid": "", "kyc_consent": false, "machine_code": "android_gcm", "rating_count": [0, 0, 0, 0, 0, 75], "hide_likes": 0, "id_address_limit_info": "{}", "birth_timestamp": 289752120, "score": -1, "ba_check_status": 2, "rating_star": 5.0, "following_count": 24, "followed": false, "wallet_setting": 1}], "order": {"ship_by_date": 1508146274, "origin_shipping_fee": "60.00", "logistics_flag": 2056, "order_command": "", "first_item_model": "ä¸æ®ºâ1.8m", "first_item_is_wholesale": false, "is_request_cancellation": false, "buyer_rate_cmtid": 0, "escrow_release_time": 1509960674, "seller_due_date": 0, "pickup_attempts": 0, "shipping_remark": "", "comm_fee": "9.00", "seller_is_rated": 0, "buyer_address_zipcode": "", "actual_shipping_fee": "0.00", "pickup_date_description": "", "credit_card_promotion": "0.00", "note": "", "id": 259405162, "rate_by_date": 0, "buyer_is_rated": 0, "logistics_status": 9, "logistics_extra_data": "{\"discounted_shipping_fees\": {\"shopee\": 0, \"seller\": 6000000}, \"extra_flag\": 0}", "first_item_name": "è¶æ®  ç¾¤å Powersync 18 2P+3P ²é·æç£µå»¶·ç PWS-EAMS1845", "rate_star": 0, "ordersn": "17101317309CBNA", "return_id": 0, "pickup_cutoff_time": 0, "voucher_code": "SM213", "shipping_method": 8, "coin_used": 0, "userid": 1293514, "complete_time": 0, "payby_date": 1508146239, "shipping_rebate": "0.00", "first_item_return": false, "seller_rate_cmtid": 0, "rate_comment": "", "buyer_address_name": "*", "waybill_printed": false, "paid_amount": "0.00", "create_time": 1507887038, "shipping_address": "è«å¯æ³¨æä½è¨®ç¦ï", "list_type": 7, "payment_channel_name": "è²¨å°äæ¬", "seller_address": {"address": "", "geoinfo": "", "logistics_status": 0, "id": 0, "full_address": "", "command": "", "phone": "", "zipcode": "", "district": "", "name": "", "storeid": "", "country": "", "state": "", "orderid": 0, "status": 0, "userid": 0, "city": "", "town": ""}, "order_type": 2, "pay_by_wallet": false, "cancel_userid": 0, "logistics_channel": 30006, "currency": "TWD", "status_ext": 1, "used_voucher": 4200000, "voucher_absorbed_by_seller": false, "logid": 0, "shopid": 10966219, "cancel_reason": -1, "arrange_pickup_by_date": 1508146274, "seller_userid": 10967519, "seller_address_id": 0, "payment_method": 6, "first_item_count": 1, "shipping_proof_status": 0, "actual_price": "257.00", "checkoutid": 237779428, "shipping_confirm_time": 1507887074, "actual_carrier": "¨å®¶", "buyer_address_phone": "886920330625", "note_mtime": "0", "coin_offset": "0.00", "card_txn_fee_info": {"rule_id": 0, "card_txn_fee": "0.00"}, "cancellation_end_date": null, "buyer_paid_amount": "299.00", "is_buyercancel_toship": false, "item_count": 1, "instant_buyercancel_toship": false, "remark": "", "pickup_time": 0, "credit_card_number": "", "estimated_shipping_rebate": "0.00", "order_items": ["order-259405162-85380463-69480570"], "shipping_traceno": "", "shipping_proof": "", "cancel_reason_ext": 0, "price_before_discount": "299.00", "buyer_cancel_reason": 0, "total_price": "257.00", "shipping_fee": "0.00", "pay_by_credit_card": false, "wallet_discount": "0.00", "voucher_price": "42.00", "status": 1, "delivery_time": 0}}